{
    "version": {
        "id": 287562,
        "crate": "zwp-virtual-keyboard",
        "num": "0.2.0",
        "dl_path": "/api/v1/crates/zwp-virtual-keyboard/0.2.0/download",
        "readme_path": "/api/v1/crates/zwp-virtual-keyboard/0.2.0/readme",
        "updated_at": "2022-10-08T22:26:30.972473Z",
        "created_at": "2020-09-26T00:13:40.361793Z",
        "downloads": 1978,
        "features": {},
        "yanked": true,
        "yank_message": null,
        "lib_links": null,
        "license": "MIT",
        "links": {
            "dependencies": "/api/v1/crates/zwp-virtual-keyboard/0.2.0/dependencies",
            "version_downloads": "/api/v1/crates/zwp-virtual-keyboard/0.2.0/downloads",
            "authors": "/api/v1/crates/zwp-virtual-keyboard/0.2.0/authors"
        },
        "crate_size": 15943,
        "published_by": {
            "id": 98353,
            "login": "grelltrier",
            "name": null,
            "avatar": "https://avatars.githubusercontent.com/u/67273701?v=4",
            "url": "https://github.com/grelltrier"
        },
        "audit_actions": [
            {
                "action": "publish",
                "user": {
                    "id": 98353,
                    "login": "grelltrier",
                    "name": null,
                    "avatar": "https://avatars.githubusercontent.com/u/67273701?v=4",
                    "url": "https://github.com/grelltrier"
                },
                "time": "2020-09-26T00:13:40.361793Z"
            },
            {
                "action": "yank",
                "user": {
                    "id": 156020,
                    "login": "pentamassiv",
                    "name": null,
                    "avatar": "https://avatars.githubusercontent.com/u/91755244?v=4",
                    "url": "https://github.com/pentamassiv"
                },
                "time": "2022-10-08T22:26:30.975480Z"
            }
        ],
        "checksum": "663076c809a85cb75cf44f35797c5084dbeed8ce5a96c639ed1fdfbc9aaf7180",
        "rust_version": null,
        "has_lib": true,
        "bin_names": [],
        "edition": "2018",
        "description": "(Unsafe) Rust code generated with wayland-scanner crate for virtual_keyboard_unstable_v1 protocol",
        "homepage": null,
        "documentation": null,
        "repository": "https://github.com/grelltrier/zwp-virtual-keyboard",
        "trustpub_data": null,
        "linecounts": {
            "languages": {
                "Rust": {
                    "code_lines": 31,
                    "comment_lines": 11,
                    "files": 2
                }
            },
            "total_code_lines": 31,
            "total_comment_lines": 11
        }
    }
}