{
    "version": {
        "id": 1170388,
        "crate": "ztopic",
        "num": "0.3.5",
        "dl_path": "/api/v1/crates/ztopic/0.3.5/download",
        "readme_path": "/api/v1/crates/ztopic/0.3.5/readme",
        "updated_at": "2024-06-11T06:33:41.881812Z",
        "created_at": "2024-06-11T06:33:41.881812Z",
        "downloads": 967,
        "features": {},
        "yanked": false,
        "yank_message": null,
        "lib_links": null,
        "license": "MIT",
        "links": {
            "dependencies": "/api/v1/crates/ztopic/0.3.5/dependencies",
            "version_downloads": "/api/v1/crates/ztopic/0.3.5/downloads",
            "authors": "/api/v1/crates/ztopic/0.3.5/authors"
        },
        "crate_size": 13391,
        "published_by": {
            "id": 117200,
            "login": "zsl99a",
            "name": "Ethereal",
            "avatar": "https://avatars.githubusercontent.com/u/7685960?v=4",
            "url": "https://github.com/zsl99a"
        },
        "audit_actions": [
            {
                "action": "publish",
                "user": {
                    "id": 117200,
                    "login": "zsl99a",
                    "name": "Ethereal",
                    "avatar": "https://avatars.githubusercontent.com/u/7685960?v=4",
                    "url": "https://github.com/zsl99a"
                },
                "time": "2024-06-11T06:33:41.881812Z"
            }
        ],
        "checksum": "c0e4301278d9bda95616808c26ba5e96682cdd918fa25a7bc3ac22608988afe5",
        "rust_version": null,
        "has_lib": true,
        "bin_names": [
            "hash",
            "non_null",
            "topic",
            "vector"
        ],
        "edition": "2021",
        "description": "A topic-based pub/sub library for Rust",
        "homepage": null,
        "documentation": null,
        "repository": "https://github.com/zsl99a/ztopic",
        "trustpub_data": null,
        "linecounts": {
            "languages": {
                "Rust": {
                    "code_lines": 836,
                    "comment_lines": 0,
                    "files": 22
                }
            },
            "total_code_lines": 836,
            "total_comment_lines": 0
        }
    }
}