{
    "version": {
        "id": 1775413,
        "crate": "zksync_solidity_vk_codegen",
        "num": "0.32.4",
        "dl_path": "/api/v1/crates/zksync_solidity_vk_codegen/0.32.4/download",
        "readme_path": "/api/v1/crates/zksync_solidity_vk_codegen/0.32.4/readme",
        "updated_at": "2025-10-15T09:12:57.437708Z",
        "created_at": "2025-10-15T09:12:57.437708Z",
        "downloads": 229,
        "features": {},
        "yanked": false,
        "yank_message": null,
        "lib_links": null,
        "license": "MIT OR Apache-2.0",
        "links": {
            "dependencies": "/api/v1/crates/zksync_solidity_vk_codegen/0.32.4/dependencies",
            "version_downloads": "/api/v1/crates/zksync_solidity_vk_codegen/0.32.4/downloads",
            "authors": "/api/v1/crates/zksync_solidity_vk_codegen/0.32.4/authors"
        },
        "crate_size": 26775,
        "published_by": {
            "id": 297400,
            "login": "CratesMatterLabs",
            "name": null,
            "avatar": "https://avatars.githubusercontent.com/u/185927582?v=4",
            "url": "https://github.com/CratesMatterLabs"
        },
        "audit_actions": [
            {
                "action": "publish",
                "user": {
                    "id": 297400,
                    "login": "CratesMatterLabs",
                    "name": null,
                    "avatar": "https://avatars.githubusercontent.com/u/185927582?v=4",
                    "url": "https://github.com/CratesMatterLabs"
                },
                "time": "2025-10-15T09:12:57.437708Z"
            }
        ],
        "checksum": "aebfa0660e3932458a7b9c331f22d9b8bf3bba4f8a02422ade99e872ed643501",
        "rust_version": null,
        "has_lib": true,
        "bin_names": [],
        "edition": "2018",
        "description": "ZKsync solidity codegen for vks",
        "homepage": "https://zksync.io/",
        "documentation": null,
        "repository": "https://github.com/matter-labs/zksync-crypto/",
        "trustpub_data": null,
        "linecounts": {
            "languages": {
                "Rust": {
                    "code_lines": 794,
                    "comment_lines": 15,
                    "files": 5
                },
                "Solidity": {
                    "code_lines": 968,
                    "comment_lines": 72,
                    "files": 5
                }
            },
            "total_code_lines": 1762,
            "total_comment_lines": 87
        }
    }
}