{
    "version": {
        "id": 1454635,
        "crate": "zngur-parser",
        "num": "0.6.0",
        "dl_path": "/api/v1/crates/zngur-parser/0.6.0/download",
        "readme_path": "/api/v1/crates/zngur-parser/0.6.0/readme",
        "updated_at": "2025-02-21T08:59:05.262426Z",
        "created_at": "2025-02-21T08:59:05.262426Z",
        "downloads": 2117,
        "features": {},
        "yanked": false,
        "yank_message": null,
        "lib_links": null,
        "license": "MIT OR Apache-2.0",
        "links": {
            "dependencies": "/api/v1/crates/zngur-parser/0.6.0/dependencies",
            "version_downloads": "/api/v1/crates/zngur-parser/0.6.0/downloads",
            "authors": "/api/v1/crates/zngur-parser/0.6.0/authors"
        },
        "crate_size": 14023,
        "published_by": {
            "id": 139698,
            "login": "HKalbasi",
            "name": null,
            "avatar": "https://avatars.githubusercontent.com/u/45197576?v=4",
            "url": "https://github.com/HKalbasi"
        },
        "audit_actions": [
            {
                "action": "publish",
                "user": {
                    "id": 139698,
                    "login": "HKalbasi",
                    "name": null,
                    "avatar": "https://avatars.githubusercontent.com/u/45197576?v=4",
                    "url": "https://github.com/HKalbasi"
                },
                "time": "2025-02-21T08:59:05.262426Z"
            }
        ],
        "checksum": "a86e226147f67dc3ff5774ef6d15c84b90181f3f38b94c2484a67ff89ef07f4b",
        "rust_version": "1.85",
        "has_lib": true,
        "bin_names": [],
        "edition": "2024",
        "description": "Parser of the zng file",
        "homepage": null,
        "documentation": null,
        "repository": null,
        "trustpub_data": null,
        "linecounts": {
            "languages": {
                "Rust": {
                    "code_lines": 1243,
                    "comment_lines": 2,
                    "files": 2
                }
            },
            "total_code_lines": 1243,
            "total_comment_lines": 2
        }
    }
}