{
    "version": {
        "id": 1568871,
        "crate": "zng-env",
        "num": "0.5.0",
        "dl_path": "/api/v1/crates/zng-env/0.5.0/download",
        "readme_path": "/api/v1/crates/zng-env/0.5.0/readme",
        "updated_at": "2025-05-19T00:38:34.203359Z",
        "created_at": "2025-05-18T21:38:16.774112Z",
        "downloads": 451,
        "features": {
            "built_res": []
        },
        "yanked": true,
        "yank_message": null,
        "lib_links": null,
        "license": "Apache-2.0 OR MIT",
        "links": {
            "dependencies": "/api/v1/crates/zng-env/0.5.0/dependencies",
            "version_downloads": "/api/v1/crates/zng-env/0.5.0/downloads",
            "authors": "/api/v1/crates/zng-env/0.5.0/authors"
        },
        "crate_size": 18803,
        "published_by": {
            "id": 80740,
            "login": "SamRodri",
            "name": "Samuel",
            "avatar": "https://avatars.githubusercontent.com/u/449925?v=4",
            "url": "https://github.com/SamRodri"
        },
        "audit_actions": [
            {
                "action": "publish",
                "user": {
                    "id": 80740,
                    "login": "SamRodri",
                    "name": "Samuel",
                    "avatar": "https://avatars.githubusercontent.com/u/449925?v=4",
                    "url": "https://github.com/SamRodri"
                },
                "time": "2025-05-18T21:38:16.774112Z"
            },
            {
                "action": "yank",
                "user": {
                    "id": 80740,
                    "login": "SamRodri",
                    "name": "Samuel",
                    "avatar": "https://avatars.githubusercontent.com/u/449925?v=4",
                    "url": "https://github.com/SamRodri"
                },
                "time": "2025-05-19T00:38:34.208341Z"
            }
        ],
        "checksum": "34e487c203cccdba665cd757e24d081c93115ddaf7adaeb6b5498896d4022d81",
        "rust_version": null,
        "has_lib": true,
        "bin_names": [],
        "edition": "2024",
        "description": "Part of the zng project.",
        "homepage": null,
        "documentation": "https://zng-ui.github.io/doc/zng_env",
        "repository": "https://github.com/zng-ui/zng",
        "trustpub_data": null,
        "linecounts": {
            "languages": {
                "Rust": {
                    "code_lines": 836,
                    "comment_lines": 6,
                    "files": 2
                }
            },
            "total_code_lines": 836,
            "total_comment_lines": 6
        }
    }
}